{
  "armor": {
    "ctArmor": 15,
    "hdArmor": 9,
    "laArmor": 10,
    "llArmor": 14,
    "ltArmor": 10,
    "raArmor": 10,
    "rlArmor": 14,
    "rtArmor": 10,
    "rtcArmor": 5,
    "rtlArmor": 4,
    "rtrArmor": 4,
    "type": "Ferro-Fibrous(Clan)"
  },
  "chassis": {
    "engine": "not-available",
    "mass": 30,
    "myomer": "not-available",
    "structure": "not-available"
  },
  "config": {
    "configuration": "Biped",
    "era": "2954",
    "rulesLevel": 2,
    "techBase": "Clan"
  },
  "info": {
    "model": "(Standard)",
    "name": "Vixen (Incubus)",
    "version": "1.0"
  },
  "slots": {
    "centerTorso": [
      "Fusion Engine",
      "Fusion Engine",
      "Fusion Engine",
      "Gyro",
      "Gyro",
      "Gyro",
      "Gyro",
      "Fusion Engine",
      "Fusion Engine",
      "Fusion Engine",
      "Clan Machine Gun Ammo - Half",
      "Endo Steel"
    ],
    "head": [
      "Life Support",
      "Sensors",
      "Cockpit",
      "Sensors",
      "Life Support"
    ],
    "leftArm": [
      "Shoulder",
      "Upper Arm Actuator",
      "Lower Arm Actuator",
      "Hand Actuator"
    ],
    "leftLeg": [
      "Hip",
      "Upper Leg Actuator",
      "Lower Leg Actuator",
      "Foot Actuator",
      "Endo Steel",
      "Ferro-Fibrous"
    ],
    "leftTorso": [
      "Fusion Engine",
      "Fusion Engine",
      "CLERMediumLaser",
      "CLMG",
      "CLMG",
      "Endo Steel",
      "Endo Steel",
      "Ferro-Fibrous",
      "Ferro-Fibrous",
      "Ferro-Fibrous"
    ],
    "rightArm": [
      "Shoulder",
      "Upper Arm Actuator",
      "Lower Arm Actuator",
      "Hand Actuator",
      "CLLargePulseLaser",
      "CLLargePulseLaser"
    ],
    "rightLeg": [
      "Hip",
      "Upper Leg Actuator",
      "Lower Leg Actuator",
      "Foot Actuator",
      "Endo Steel",
      "Ferro-Fibrous"
    ],
    "rightTorso": [
      "Fusion Engine",
      "Fusion Engine",
      "CLERMediumLaser",
      "CLMG",
      "CLMG",
      "Endo Steel",
      "Endo Steel",
      "Ferro-Fibrous",
      "Ferro-Fibrous"
    ]
  },
  "temperature": {
    "heatSinksCount": 10,
    "heatSinksType": "Double",
    "jumpMp": 0,
    "walkMp": 9
  },
  "weapons": [
    {
      "slot": "rightArm",
      "weapon": "Large Pulse Laser"
    },
    {
      "slot": "leftTorso",
      "weapon": "ER Medium Laser"
    },
    {
      "slot": "leftTorso",
      "weapon": "Machine Gun"
    },
    {
      "slot": "leftTorso",
      "weapon": "Machine Gun"
    },
    {
      "slot": "rightTorso",
      "weapon": "ER Medium Laser"
    },
    {
      "slot": "rightTorso",
      "weapon": "Machine Gun"
    },
    {
      "slot": "rightTorso",
      "weapon": "Machine Gun"
    }
  ]
}